{
    "type": "FeatureCollection",
    "name": "names_numbers_v3",
    "crs": { "type": "name", "properties": { "name": "urn:ogc:def:crs:OGC:1.3:CRS84" } },
    "features": [
    { "type": "Feature", "properties": { "id": 1, "name": "1.5" }, "geometry": { "type": "Point", "coordinates": [ 171.264275195521378, 7.064681245805906 ] } },
    { "type": "Feature", "properties": { "id": 2, "name": "1.4" }, "geometry": { "type": "Point", "coordinates": [ 171.268840778690617, 7.06693949124446 ] } },
    { "type": "Feature", "properties": { "id": 3, "name": "1.3" }, "geometry": { "type": "Point", "coordinates": [ 171.274879130624129, 7.067479506458027 ] } },
    { "type": "Feature", "properties": { "id": 4, "name": "1.2" }, "geometry": { "type": "Point", "coordinates": [ 171.280917482557669, 7.06973775189658 ] } },
    { "type": "Feature", "properties": { "id": 5, "name": "1.1" }, "geometry": { "type": "Point", "coordinates": [ 171.285139419681911, 7.069885028773008 ] } },
    { "type": "Feature", "properties": { "id": 6, "name": "3.1" }, "geometry": { "type": "Point", "coordinates": [ 171.357961698538702, 7.126200024396939 ] } },
    { "type": "Feature", "properties": { "id": 7, "name": "3.3" }, "geometry": { "type": "Point", "coordinates": [ 171.365853284500645, 7.121474891278226 ] } },
    { "type": "Feature", "properties": { "id": 8, "name": "3.4" }, "geometry": { "type": "Point", "coordinates": [ 171.366509893908045, 7.118290028825482 ] } },
    { "type": "Feature", "properties": { "id": 9, "name": "4.1" }, "geometry": { "type": "Point", "coordinates": [ 171.379592989764063, 7.102617314558999 ] } },
    { "type": "Feature", "properties": { "id": 10, "name": "4.2" }, "geometry": { "type": "Point", "coordinates": [ 171.380636200972106, 7.099659503957414 ] } },
    { "type": "Feature", "properties": { "id": 11, "name": "4.3" }, "geometry": { "type": "Point", "coordinates": [ 171.381274400769939, 7.096493051114225 ] } },
    { "type": "Feature", "properties": { "id": 12, "name": "2.1" }, "geometry": { "type": "Point", "coordinates": [ 171.379445712887588, 7.095916216681553 ] } },
    { "type": "Feature", "properties": { "id": 13, "name": "2.2" }, "geometry": { "type": "Point", "coordinates": [ 171.378500686263862, 7.094750274743169 ] } },
    { "type": "Feature", "properties": { "id": 14, "name": "2.3" }, "geometry": { "type": "Point", "coordinates": [ 171.379114339915645, 7.091755644922479 ] } },
    { "type": "Feature", "properties": { "id": 15, "name": "2.4" }, "geometry": { "type": "Point", "coordinates": [ 171.377580205786188, 7.08881010739393 ] } },
    { "type": "Feature", "properties": { "id": 16, "name": "2.5" }, "geometry": { "type": "Point", "coordinates": [ 171.375530602589237, 7.087766896185903 ] } },
    { "type": "Feature", "properties": { "id": 3, "name": "3.2" }, "geometry": { "type": "Point", "coordinates": [ 171.363245256480553, 7.124942034410788 ] } }
    ]
    }
    